drf_oauth2/__init__.py
drf_oauth2/handlers/base.py
drf_oauth2/handlers/jwt.py
drf_oauth2/handlers/session.py
drf_oauth2/handlers/token.py
drf_oauth2/migrations/0001_initial.py
drf_oauth2/migrations/__init__.py
drf_oauth2/models.py
drf_oauth2/providers/__init__.py
drf_oauth2/providers/base.py
drf_oauth2/providers/facebook.py
drf_oauth2/providers/github.py
drf_oauth2/providers/google.py
drf_oauth2/serializers.py
drf_oauth2/settings.py
drf_oauth2/urls.py
drf_oauth2/views.py
drf_oauth2_tools-1.0.2.dist-info/LICENSE
drf_oauth2_tools-1.0.2.dist-info/METADATA
drf_oauth2_tools-1.0.2.dist-info/WHEEL
drf_oauth2_tools-1.0.2.dist-info/RECORD
