Metadata-Version: 2.3
Name: drf-oauth2-tools
Version: 1.0.2
Summary: Comprehensive Django REST Framework library for OAuth social login
Keywords: django,django-rest-framework,oauth,social-login,authentication,google-oauth,facebook-oauth,github-oauth,jwt,social-auth
Author: Vladyslav Chaliuk
Author-email: chaliukvladyslav@gmail.com
Requires-Python: >=3.11
Classifier: Development Status :: 5 - Production/Stable
Classifier: Environment :: Web Environment
Classifier: Framework :: Django
Classifier: Framework :: Django :: 4.2
Classifier: Framework :: Django :: 5.0
Classifier: Intended Audience :: Developers
Classifier: License :: OSI Approved :: MIT License
Classifier: Operating System :: OS Independent
Classifier: Programming Language :: Python
Classifier: Programming Language :: Python :: 3
Classifier: Programming Language :: Python :: 3.10
Classifier: Programming Language :: Python :: 3.11
Classifier: Programming Language :: Python :: 3.12
Classifier: Programming Language :: Python :: 3.13
Classifier: Topic :: Internet :: WWW/HTTP
Classifier: Topic :: Internet :: WWW/HTTP :: Dynamic Content
Classifier: Topic :: Software Development :: Libraries :: Application Frameworks
Classifier: Topic :: Software Development :: Libraries :: Python Modules
Classifier: Topic :: System :: Systems Administration :: Authentication/Directory
Requires-Dist: django (>=5.0.0,<6.0.0)
Requires-Dist: djangorestframework (>=3.15.0,<4.0.0)
Requires-Dist: djangorestframework-simplejwt (>=5.5.1,<6.0.0)
Requires-Dist: requests (>=2.32.4,<3.0.0)
Project-URL: Homepage, https://github.com/AstralMortem/drf-oauth2-tools
Project-URL: Repository, https://github.com/AstralMortem/drf-oauth2-tools.git
